{"nodes": [{"id": "c_users_serhi_documents_development_habit_pet_mobile_notifications_md", "label": "NOTIFICATIONS.md", "file_type": "document", "source_file": "NOTIFICATIONS.md", "source_location": "L1"}, {"id": "mobile_notifications_notifications", "label": "NOTIFICATIONS", "file_type": "document", "source_file": "NOTIFICATIONS.md", "source_location": "L1"}, {"id": "mobile_notifications_overview", "label": "Overview", "file_type": "document", "source_file": "NOTIFICATIONS.md", "source_location": "L3"}, {"id": "mobile_notifications_current_implementation", "label": "Current Implementation", "file_type": "document", "source_file": "NOTIFICATIONS.md", "source_location": "L7"}, {"id": "mobile_notifications_rules", "label": "Rules", "file_type": "document", "source_file": "NOTIFICATIONS.md", "source_location": "L16"}, {"id": "mobile_notifications_notification_types", "label": "Notification Types", "file_type": "document", "source_file": "NOTIFICATIONS.md", "source_location": "L18"}, {"id": "mobile_notifications_scheduling", "label": "Scheduling", "file_type": "document", "source_file": "NOTIFICATIONS.md", "source_location": "L24"}, {"id": "mobile_notifications_user_preferences", "label": "User Preferences", "file_type": "document", "source_file": "NOTIFICATIONS.md", "source_location": "L33"}, {"id": "mobile_notifications_notification_content", "label": "Notification Content", "file_type": "document", "source_file": "NOTIFICATIONS.md", "source_location": "L40"}, {"id": "mobile_notifications_device_reboot_handling", "label": "Device Reboot Handling", "file_type": "document", "source_file": "NOTIFICATIONS.md", "source_location": "L51"}, {"id": "mobile_notifications_configuration", "label": "Configuration", "file_type": "document", "source_file": "NOTIFICATIONS.md", "source_location": "L56"}, {"id": "mobile_notifications_data_model", "label": "Data Model", "file_type": "document", "source_file": "NOTIFICATIONS.md", "source_location": "L73"}, {"id": "mobile_notifications_source_files", "label": "Source Files", "file_type": "document", "source_file": "NOTIFICATIONS.md", "source_location": "L82"}, {"id": "mobile_notifications_known_gaps", "label": "Known Gaps", "file_type": "document", "source_file": "NOTIFICATIONS.md", "source_location": "L91"}], "edges": [{"source": "c_users_serhi_documents_development_habit_pet_mobile_notifications_md", "target": "mobile_notifications_notifications", "relation": "contains", "confidence": "EXTRACTED", "source_file": "NOTIFICATIONS.md", "source_location": "L1", "weight": 1.0}, {"source": "mobile_notifications_notifications", "target": "mobile_notifications_overview", "relation": "contains", "confidence": "EXTRACTED", "source_file": "NOTIFICATIONS.md", "source_location": "L3", "weight": 1.0}, {"source": "mobile_notifications_notifications", "target": "mobile_notifications_current_implementation", "relation": "contains", "confidence": "EXTRACTED", "source_file": "NOTIFICATIONS.md", "source_location": "L7", "weight": 1.0}, {"source": "mobile_notifications_notifications", "target": "mobile_notifications_rules", "relation": "contains", "confidence": "EXTRACTED", "source_file": "NOTIFICATIONS.md", "source_location": "L16", "weight": 1.0}, {"source": "mobile_notifications_rules", "target": "mobile_notifications_notification_types", "relation": "contains", "confidence": "EXTRACTED", "source_file": "NOTIFICATIONS.md", "source_location": "L18", "weight": 1.0}, {"source": "mobile_notifications_rules", "target": "mobile_notifications_scheduling", "relation": "contains", "confidence": "EXTRACTED", "source_file": "NOTIFICATIONS.md", "source_location": "L24", "weight": 1.0}, {"source": "mobile_notifications_rules", "target": "mobile_notifications_user_preferences", "relation": "contains", "confidence": "EXTRACTED", "source_file": "NOTIFICATIONS.md", "source_location": "L33", "weight": 1.0}, {"source": "mobile_notifications_rules", "target": "mobile_notifications_notification_content", "relation": "contains", "confidence": "EXTRACTED", "source_file": "NOTIFICATIONS.md", "source_location": "L40", "weight": 1.0}, {"source": "mobile_notifications_rules", "target": "mobile_notifications_device_reboot_handling", "relation": "contains", "confidence": "EXTRACTED", "source_file": "NOTIFICATIONS.md", "source_location": "L51", "weight": 1.0}, {"source": "mobile_notifications_notifications", "target": "mobile_notifications_configuration", "relation": "contains", "confidence": "EXTRACTED", "source_file": "NOTIFICATIONS.md", "source_location": "L56", "weight": 1.0}, {"source": "mobile_notifications_notifications", "target": "mobile_notifications_data_model", "relation": "contains", "confidence": "EXTRACTED", "source_file": "NOTIFICATIONS.md", "source_location": "L73", "weight": 1.0}, {"source": "mobile_notifications_notifications", "target": "mobile_notifications_source_files", "relation": "contains", "confidence": "EXTRACTED", "source_file": "NOTIFICATIONS.md", "source_location": "L82", "weight": 1.0}, {"source": "mobile_notifications_notifications", "target": "mobile_notifications_known_gaps", "relation": "contains", "confidence": "EXTRACTED", "source_file": "NOTIFICATIONS.md", "source_location": "L91", "weight": 1.0}], "input_tokens": 0, "output_tokens": 0}